MANIFEST.in
setup.py
trader_tweets_core/__init__.py
trader_tweets_core/prompt_factory.py
trader_tweets_core/tweet_parsing.py
trader_tweets_core.egg-info/PKG-INFO
trader_tweets_core.egg-info/SOURCES.txt
trader_tweets_core.egg-info/dependency_links.txt
trader_tweets_core.egg-info/requires.txt
trader_tweets_core.egg-info/top_level.txt
trader_tweets_core/model/__init__.py
trader_tweets_core/model/classified_tweet.py
trader_tweets_core/model/db_classified_tweet.py
trader_tweets_core/model/trade.py
trader_tweets_core/model/tweet_stance.py
trader_tweets_core/model/tweet_type.py
trader_tweets_core/model/prompt/__init__.py
trader_tweets_core/model/prompt/bullish_bearish.py
trader_tweets_core/model/prompt/buying_selling.py
trader_tweets_core/model/prompt/prompt.py
trader_tweets_core/model/prompt/stance.py
trader_tweets_core/model/twitter/__init__.py
trader_tweets_core/model/twitter/simple_tweet.py
trader_tweets_core/model/twitter/twitter_traders.py
trader_tweets_core/model/twitter/twitter_user.py
trader_tweets_core/repository/__init__.py
trader_tweets_core/repository/mapper/__init__.py
trader_tweets_core/repository/mapper/classified_tweet_mapper.py
trader_tweets_core/res/quick-shot-training-tweets.json
trader_tweets_core/res/prompts/examples-letter-2.prompt
trader_tweets_core/res/prompts/examples-letter-extended.prompt
trader_tweets_core/res/prompts/examples-letter.prompt
trader_tweets_core/res/prompts/examples-word-2-test.prompt
trader_tweets_core/res/prompts/examples-word-2.prompt
trader_tweets_core/res/prompts/examples-word.prompt
trader_tweets_core/res/prompts/is-buying-or-selling.prompt
trader_tweets_core/res/prompts/simple-openai-example-hyphen-one-line.prompt
trader_tweets_core/res/prompts/simple-openai-example-separator-hyphen.prompt
trader_tweets_core/res/prompts/simple-openai-example-separator.prompt
trader_tweets_core/res/prompts/simple-openai-example.prompt
trader_tweets_core/res/prompts/simple.prompt
trader_tweets_core/res/training/open-close/results-50.csv
trader_tweets_core/res/training/open-close/results.csv
trader_tweets_core/res/training/open-close/training-batch-1.json
trader_tweets_core/res/training/open-close/training-tweets-batch-1.jsonl
