Metadata-Version: 2.1
Name: trader-tweets-core
Version: 0.1.16
Author: Will H-S
Author-email: whardwicksmith@gmail.com
Classifier: Programming Language :: Python :: 3
Classifier: License :: OSI Approved :: MIT License
Classifier: Operating System :: OS Independent
Requires-Python: >=3.11
Requires-Dist: openai==1.35.7
Requires-Dist: requests==2.31.0
Requires-Dist: setuptools~=69.1.1
Requires-Dist: parameterized==0.9.0
Requires-Dist: diskcache==5.6.3
